hasy_tools/__init__.py
hasy_tools/_version.py
hasy_tools/hasy.py
tests/__init__.py
tests/test_hasy_tools.py
hasy_tools-0.1.2.dist-info/METADATA
hasy_tools-0.1.2.dist-info/WHEEL
hasy_tools-0.1.2.dist-info/top_level.txt
hasy_tools-0.1.2.dist-info/RECORD
