Metadata-Version: 2.1
Name: hasy-tools
Version: 0.1.2
Summary: Convenience functions for the HASY dataset
Home-page: https://github.com/MartinThoma/hasy_tools
Author: Martin Thoma
Author-email: info@martin-thoma.de
Maintainer: Martin Thoma
Maintainer-email: info@martin-thoma.de
License: MIT
Download-URL: https://github.com/MartinThoma/hasy_tools
Keywords: Machine Learning,Data Science,classifiers,Classification,utility
Platform: Linux
Classifier: Development Status :: 7 - Inactive
Classifier: Environment :: Console
Classifier: Intended Audience :: Developers
Classifier: Intended Audience :: Information Technology
Classifier: Intended Audience :: Science/Research
Classifier: License :: OSI Approved :: MIT License
Classifier: Natural Language :: English
Classifier: Operating System :: OS Independent
Classifier: Programming Language :: Python :: 3
Classifier: Programming Language :: Python :: 3 :: Only
Classifier: Programming Language :: Python :: 3.8
Classifier: Topic :: Software Development :: Libraries :: Python Modules
Classifier: Topic :: Scientific/Engineering :: Information Analysis
Classifier: Topic :: Scientific/Engineering :: Visualization
Classifier: Topic :: Software Development
Classifier: Topic :: Utilities
Requires-Python: >=3.8
Requires-Dist: Pillow
Requires-Dist: scikit-learn
Requires-Dist: matplotlib
